discordspy/__init__.py
discordspy/client.py
discordspy/utils.py
discordspy-0.1.2.dist-info/LICENSE.md
discordspy-0.1.2.dist-info/METADATA
discordspy-0.1.2.dist-info/WHEEL
discordspy-0.1.2.dist-info/top_level.txt
discordspy-0.1.2.dist-info/RECORD
