Metadata-Version: 2.1
Name: discordspy
Version: 0.1.2
Summary: A basic API wrapper for Discords.com
Home-page: https://github.com/judev1/discords
Author: Jude BC
Author-email: jude.version1.0@gmail.com
License: MIT
Platform: UNKNOWN
Classifier: Development Status :: 5 - Production/Stable
Classifier: Intended Audience :: Developers
Classifier: License :: OSI Approved :: MIT License
Classifier: Programming Language :: Python :: 3
